LICENSE
MANIFEST.in
README.md
setup.py
yasal/__init__.py
yasal/yasal.py
yasal.egg-info/PKG-INFO
yasal.egg-info/SOURCES.txt
yasal.egg-info/dependency_links.txt
yasal.egg-info/entry_points.txt
yasal.egg-info/not-zip-safe
yasal.egg-info/requires.txt
yasal.egg-info/top_level.txt