Metadata-Version: 1.1
Name: yasal
Version: 1.0.5
Summary: Yet another save as link
Home-page: https://github.com/WnP/yasal
Author: Steeve
Author-email: mo0ofier@gmail.com
License: MIT
Platform: UNKNOWN
Classifier: Development Status :: 5 - Production/Stable
Classifier: Environment :: Console
Classifier: Intended Audience :: End Users/Desktop
Classifier: License :: OSI Approved :: MIT License
Classifier: Operating System :: OS Independent
Classifier: Programming Language :: Python
Classifier: Programming Language :: Python :: 2.7
